catchment_simulation/__init__.py
catchment_simulation/catchment_features_simulation.py
catchment_simulation-0.0.6.dist-info/LICENSE
catchment_simulation-0.0.6.dist-info/METADATA
catchment_simulation-0.0.6.dist-info/WHEEL
catchment_simulation-0.0.6.dist-info/top_level.txt
catchment_simulation-0.0.6.dist-info/RECORD
