Metadata-Version: 2.1
Name: catchment-simulation
Version: 0.0.6
Summary: ('Collection of calculation method for simulate subcatchment features from Storm Water Management Model',)
Home-page: UNKNOWN
Author: Rafał Buczyński
License: UNKNOWN
Project-URL: Homepage, https://github.com/BuczynskiRafal/catchments_simulation
Platform: UNKNOWN
License-File: LICENSE
Requires-Dist: pandas
Requires-Dist: numpy
Requires-Dist: swmmio
Requires-Dist: pyswmm
